pythoness/__init__.py
pythoness/foo.py
pythoness/pythoness_module.py
pythoness/test2.py
pythoness/testem.py
pythoness-0.1.0.dist-info/METADATA
pythoness-0.1.0.dist-info/WHEEL
pythoness-0.1.0.dist-info/top_level.txt
pythoness-0.1.0.dist-info/RECORD
