Metadata-Version: 2.1
Name: pythoness
Version: 0.1.0
Summary: Pythoness: use natural language to define Python functions.
Author-email: Emery Berger <emery.berger@gmail.com>
Project-URL: Homepage, https://github.com/plasma-umass/pythoness
Project-URL: Bug Tracker, https://github.com/plasma-umass/pythoness/issues
Classifier: Programming Language :: Python :: 3
Classifier: Programming Language :: Python :: 3.8
Classifier: Programming Language :: Python :: 3.9
Classifier: Programming Language :: Python :: 3.10
Classifier: Programming Language :: Python :: 3.11
Classifier: License :: OSI Approved :: MIT License
Classifier: Operating System :: OS Independent
Requires-Python: >=3.7
Requires-Dist: openai >=0.27.0
Requires-Dist: ast-comments >=1.0.0
